pyhomelink/__init__.py
pyhomelink/alert.py
pyhomelink/api.py
pyhomelink/auth.py
pyhomelink/const.py
pyhomelink/device.py
pyhomelink/exceptions.py
pyhomelink/insight.py
pyhomelink/lookup.py
pyhomelink/property.py
pyhomelink/py.typed
pyhomelink/reading.py
pyhomelink/utils.py
pyhomelink/version.py
pyhomelink-0.2.1.dist-info/LICENSE
pyhomelink-0.2.1.dist-info/METADATA
pyhomelink-0.2.1.dist-info/WHEEL
pyhomelink-0.2.1.dist-info/top_level.txt
pyhomelink-0.2.1.dist-info/RECORD
