Metadata-Version: 2.1
Name: pyhomelink
Version: 0.2.1
Summary: Library for AICO HomeLINK
Author-email: Roger Selwyn <roger.selwyn@users.noreply.github.com>
Maintainer-email: Roger Selwyn <roger.selwyn@users.noreply.github.com>
License: MIT License
Project-URL: Documentation, https://rogerselwyn.github.io/python_homelink/
Project-URL: Repository, https://github.com/RogerSelwyn/python_homelink
Project-URL: Issues, https://github.com/RogerSelwyn/python_homelink/issues
Project-URL: Changelog, https://github.com/RogerSelwyn/python_homelink/blob/main/CHANGELOG.md
Keywords: AICO HomeLINK,AICO,HomeLINK,Alarm
Platform: any
Classifier: Development Status :: 5 - Production/Stable
Classifier: Intended Audience :: Developers
Classifier: Topic :: Home Automation
Classifier: Topic :: Software Development :: Libraries
Classifier: Programming Language :: Python
Classifier: Programming Language :: Python :: 3 :: Only
Classifier: Programming Language :: Python :: 3.11
Classifier: Operating System :: OS Independent
Requires-Python: >=3.11
License-File: LICENSE
Requires-Dist: aiohttp>=3.8.5
Provides-Extra: test
Requires-Dist: tomli==2.2.0; extra == "test"
